google_maps_mcp/__init__.py
google_maps_mcp/mcp_server.py
google_maps_mcp/services/__init__.py
google_maps_mcp/services/places.py
google_maps_mcp-2.0.0.dist-info/licenses/LICENSE
google_maps_mcp-2.0.0.dist-info/METADATA
google_maps_mcp-2.0.0.dist-info/WHEEL
google_maps_mcp-2.0.0.dist-info/entry_points.txt
google_maps_mcp-2.0.0.dist-info/top_level.txt
google_maps_mcp-2.0.0.dist-info/RECORD
