Metadata-Version: 2.4
Name: google-maps-mcp
Version: 2.0.0
Summary: Google Maps MCP server using Google Places API.
Author: Mastan Shaik
Project-URL: Homepage, https://github.com/Mastan1301/google_maps_mcp
Project-URL: Bug Tracker, https://github.com/Mastan1301/google_maps_mcp/issues
Project-URL: Repository, https://github.com/Mastan1301/google_maps_mcp.git
Requires-Python: >=3.8
License-File: LICENSE
Requires-Dist: mcp==1.9.4
Requires-Dist: python-dotenv==1.1.0
Requires-Dist: googlemaps==4.10.0
Provides-Extra: dev
Requires-Dist: pytest==8.4.1; extra == "dev"
Dynamic: license-file
